setup.py
safran/__init__.py
safran/__main__.py
safran.egg-info/PKG-INFO
safran.egg-info/SOURCES.txt
safran.egg-info/dependency_links.txt
safran.egg-info/entry_points.txt
safran.egg-info/requires.txt
safran.egg-info/top_level.txt