Metadata-Version: 1.0
Name: safran
Version: 0.1
Summary: safran.io CLI reader
Home-page: http://github.com/emre/safran
Author: Emre Yilmaz
Author-email: mail@emreyilmaz.me
License: MIT
Platform: UNKNOWN
